{
  "$schema": "https://developer.microsoft.com/json-schemas/spfx-build/package-solution.schema.json",
  "solution": {
    "name": "DemoACE",
    "id": "b37407dd-905a-4924-a28a-69f57b5cb1df",
    "version": "1.0.0.0",
    "includeClientSideAssets": true,
    "skipFeatureDeployment": true,
    "isDomainIsolated": false,
    "developer": {
      "name": "Soumyadeep-Soumit-Sourav",
      "websiteUrl": "https://github.com/XLR8-0/M365",
      "privacyUrl": "https://github.com/XLR8-0/M365/privacy",
      "termsOfUseUrl": "",
      "mpnId": "Undefined-1.13.1"
    }
  },
  "paths": {
    "zippedPackage": "solution/demo-ace.sppkg"
  }
}